pylattica/__init__.py
pylattica/atomic/__init__.py
pylattica/atomic/pymatgen_struct_converter.py
pylattica/core/__init__.py
pylattica/core/analyzer.py
pylattica/core/basic_controller.py
pylattica/core/constants.py
pylattica/core/coordinate_utils.py
pylattica/core/distance_map.py
pylattica/core/lattice.py
pylattica/core/neighborhood_builders.py
pylattica/core/neighborhoods.py
pylattica/core/periodic_structure.py
pylattica/core/simulation.py
pylattica/core/simulation_result.py
pylattica/core/simulation_state.py
pylattica/core/structure_builder.py
pylattica/core/utils.py
pylattica/core/runner/__init__.py
pylattica/core/runner/asynchronous_runner.py
pylattica/core/runner/base_runner.py
pylattica/core/runner/common.py
pylattica/core/runner/synchronous_runner.py
pylattica/discrete/__init__.py
pylattica/discrete/discrete_state_result_analyzer.py
pylattica/discrete/discrete_step_analyzer.py
pylattica/discrete/phase_set.py
pylattica/discrete/state_constants.py
pylattica/models/__init__.py
pylattica/models/game_of_life/__init__.py
pylattica/models/game_of_life/controller.py
pylattica/models/game_of_life/life_phase_set.py
pylattica/models/growth/__init__.py
pylattica/models/growth/growth_controller.py
pylattica/structures/__init__.py
pylattica/structures/honeycomb/__init__.py
pylattica/structures/honeycomb/lattice.py
pylattica/structures/honeycomb/neighborhoods.py
pylattica/structures/honeycomb/structure_builders.py
pylattica/structures/square_grid/__init__.py
pylattica/structures/square_grid/grid_setup.py
pylattica/structures/square_grid/growth_setup.py
pylattica/structures/square_grid/lattice.py
pylattica/structures/square_grid/neighborhoods.py
pylattica/structures/square_grid/structure_builders.py
pylattica/visualization/__init__.py
pylattica/visualization/cell_artist.py
pylattica/visualization/colors.py
pylattica/visualization/helpers.py
pylattica/visualization/result_artist.py
pylattica/visualization/square_grid_artist_2D.py
pylattica-0.1.4.dist-info/LICENSE
pylattica-0.1.4.dist-info/METADATA
pylattica-0.1.4.dist-info/WHEEL
pylattica-0.1.4.dist-info/top_level.txt
pylattica-0.1.4.dist-info/RECORD
