Metadata-Version: 2.2
Name: pylattica
Version: 0.1.4
Summary: pylattica is a package for fast prototyping of lattice models for chemistry and materials science
Author-email: Max Gallant <maxg@lbl.gov>
License: MIT
Project-URL: homepage, https://mcgalcode.github.io/pylattica/
Project-URL: documentation, https://mcgalcode.github.io/pylattica/
Project-URL: repository, https://github.com/mcgalcode/pylattica
Project-URL: changelog, https://github.com/mcgalcode/pylattica/blob/main/docs/CHANGELOG.md
Keywords: cellular,automaton,lattice,simulation,chemistry,materials
Classifier: Programming Language :: Python :: 3
Classifier: Programming Language :: Python :: 3.8
Classifier: Programming Language :: Python :: 3.9
Classifier: Programming Language :: Python :: 3.10
Classifier: Development Status :: 4 - Beta
Classifier: Intended Audience :: Science/Research
Classifier: License :: OSI Approved :: BSD License
Classifier: Operating System :: OS Independent
Classifier: Topic :: Scientific/Engineering :: Information Analysis
Classifier: Topic :: Scientific/Engineering :: Physics
Classifier: Topic :: Scientific/Engineering :: Chemistry
Classifier: Topic :: Software Development :: Libraries :: Python Modules
Requires-Python: >=3.8
License-File: LICENSE
Requires-Dist: numpy>=1.21.5
Requires-Dist: matplotlib>=3.5.1
Requires-Dist: tqdm>=4.63.0
Requires-Dist: pymatgen>=2022.3.29
Requires-Dist: plotly>=5.6.0
Requires-Dist: monty>=2022.9.9
Requires-Dist: rustworkx>=0.12.0
Requires-Dist: pydantic>=1.10.2
Requires-Dist: maggma>=0.49.5
Requires-Dist: Pillow>=9.0
Provides-Extra: docs
Requires-Dist: jupyter_contrib_nbextensions>=0.7.0; extra == "docs"
Requires-Dist: notebook==6.4.12; extra == "docs"
Requires-Dist: mkdocs>=1.4.0; extra == "docs"
Requires-Dist: mkdocs-autorefs>=0.4.1; extra == "docs"
Requires-Dist: mkdocs-jupyter>=0.24.6; extra == "docs"
Requires-Dist: mkdocs-section-index>=0.3.4; extra == "docs"
Requires-Dist: mkdocstrings>=0.19.0; extra == "docs"
Requires-Dist: mkdocstrings-python>=0.7.1; extra == "docs"
Requires-Dist: pymdown-extensions>=9.6; extra == "docs"
Provides-Extra: jupyter
Requires-Dist: jupyterlab>=3.4.4; extra == "jupyter"
Requires-Dist: nbconvert<7.0.0,>=6.2.0; extra == "jupyter"
Provides-Extra: plotting
Requires-Dist: graphistry==0.28.0; extra == "plotting"
Provides-Extra: tests
Requires-Dist: pytest==7.1.3; extra == "tests"
Requires-Dist: pytest-cov==4.0.0; extra == "tests"
